CHANGELOG.md
README.md
promgen_k8s/__init__.py
promgen_k8s/cadvisor_job.py
promgen_k8s/cluster.py
promgen_k8s/generator.py
promgen_k8s/ingresses_job.py
promgen_k8s/nodes_job.py
promgen_k8s/pods_job.py
promgen_k8s/prom_dsl.py
promgen_k8s/service_endpoints_job.py
promgen_k8s/services_job.py
promgen_k8s-0.3.0.dist-info/LICENSE
promgen_k8s-0.3.0.dist-info/WHEEL
promgen_k8s-0.3.0.dist-info/METADATA
promgen_k8s-0.3.0.dist-info/RECORD
