Metadata-Version: 2.1
Name: promgen-k8s
Version: 0.3.0
Summary: A modular Prometheus 2 configuration file generator to monitor multiple Kubernetes clusters with a single Prometheus instance.
Home-page: https://github.com/cmur2/promgen-k8s
License: Apache-2.0
Author: Christian Nicolai
Requires-Python: >=3.7,<4.0
Classifier: License :: OSI Approved :: Apache Software License
Classifier: Programming Language :: Python :: 3
Classifier: Programming Language :: Python :: 3.7
Classifier: Programming Language :: Python :: 3.8
Classifier: Programming Language :: Python :: 3.9
Requires-Dist: pyyaml
